rallies/__init__.py
rallies/cli.py
rallies/helpers.py
rallies/llm.py
rallies/manager.py
rallies/agent/__init__.py
rallies/agent/agent.py
rallies/agent/prompts.py
rallies-0.1.0.dist-info/licenses/LICENSE
rallies-0.1.0.dist-info/METADATA
rallies-0.1.0.dist-info/WHEEL
rallies-0.1.0.dist-info/entry_points.txt
rallies-0.1.0.dist-info/top_level.txt
rallies-0.1.0.dist-info/RECORD
