Metadata-Version: 2.4
Name: rallies
Version: 0.1.0
Summary: Stock Analysis Agent
Author: Rallies Team
License: GPL-3.0
Classifier: Programming Language :: Python :: 3
Classifier: License :: OSI Approved :: GNU General Public License v3 (GPLv3)
Classifier: Operating System :: OS Independent
Requires-Python: >=3.6
License-File: LICENSE
Requires-Dist: rich
Requires-Dist: inquirer
Requires-Dist: tiktoken
Requires-Dist: requests
Requires-Dist: openai
Requires-Dist: numpy
Dynamic: license-file
Dynamic: requires-python
